{
  "version": "2026-07-05-CICD-003-admin-config-role-002",
  "source_note": "Public sanitized CI/CD environment model for Admin preview and future app dashboards.",
  "environments": [
    {
      "name": "development",
      "purpose": "Build experimental features without touching the stable public entrypoint.",
      "status": "ACTIVE / CR-016-MOBILE-002 DEV",
      "health": "yellow",
      "url_pattern": "/env/dev/",
      "promotion_rule": "Developer validation only. No owner PASS required.",
      "rollback_rule": "Delete or ignore failed dev build. Never promote directly to production."
    },
    {
      "name": "testing",
      "purpose": "Check loading, mobile layout, navigation, visual status, app scope, config, role access, and data integrity.",
      "status": "ACTIVE / CR-016-MOBILE-002 TEST",
      "health": "yellow",
      "url_pattern": "/env/test/",
      "promotion_rule": "Must pass basic smoke tests before pre-prod.",
      "rollback_rule": "Failed test build stays out of pre-prod/prod and rolls back to DEV."
    },
    {
      "name": "pre-prod",
      "purpose": "Owner-visible candidate preview before production.",
      "status": "ACTIVE / CR-016-MOBILE-002 PRE-PROD",
      "health": "yellow",
      "url_pattern": "/env/preprod/",
      "promotion_rule": "Requires owner-visible PASS before production.",
      "rollback_rule": "Revert to last owner-approved test candidate."
    },
    {
      "name": "production",
      "purpose": "Stable public Admin preview on GitHub Pages.",
      "status": "ACTIVE / CR-016-MOBILE-002",
      "health": "green",
      "url_pattern": "https://rani12k.github.io/rani-os-admin-preview/",
      "promotion_rule": "Only owner-visible PASS builds or safe patches should reach production.",
      "rollback_rule": "CR-013 is rollback target only; return entrypoint to rollback target and disable failed build files."
    }
  ],
  "required_pipeline": "Build -> Dev -> Test -> Pre-Prod -> Owner PASS -> Production -> Monitor -> Rollback if needed",
  "current_gap": "The dashboard has isolated GitHub Pages routes for dev, test, pre-prod, and production. Remaining automation should verify the same pipeline without bypassing Owner Gate.",
  "next_safe_action": "Run smoke checks across /, /env/dev/, /env/test/, and /env/preprod/ before any future owner-approved promotion."
}
